{
    "key": "post_type_68a241d7d464d",
    "title": "Groups",
    "menu_order": 0,
    "active": true,
    "post_type": "group",
    "advanced_configuration": true,
    "import_source": "",
    "import_date": "",
    "labels": {
        "name": "Groups",
        "singular_name": "Group",
        "menu_name": "Groups",
        "all_items": "All Groups",
        "edit_item": "Edit Group",
        "view_item": "View Group",
        "view_items": "View Groups",
        "add_new_item": "Add Group",
        "add_new": "Add Group",
        "new_item": "New Group",
        "parent_item_colon": "Parent Group:",
        "search_items": "Search Groups",
        "not_found": "No groups found",
        "not_found_in_trash": "No groups found in Trash",
        "archives": "Group Archives",
        "attributes": "Group Attributes",
        "featured_image": "",
        "set_featured_image": "",
        "remove_featured_image": "",
        "use_featured_image": "",
        "insert_into_item": "Insert into group",
        "uploaded_to_this_item": "Uploaded to this group",
        "filter_items_list": "Filter groups list",
        "filter_by_date": "Filter groups by date",
        "items_list_navigation": "Groups list navigation",
        "items_list": "Groups list",
        "item_published": "Group published.",
        "item_published_privately": "Group published privately.",
        "item_reverted_to_draft": "Group reverted to draft.",
        "item_scheduled": "Group scheduled.",
        "item_updated": "Group updated.",
        "item_link": "Group Link",
        "item_link_description": "A link to a group."
    },
    "description": "",
    "public": true,
    "hierarchical": false,
    "exclude_from_search": false,
    "publicly_queryable": true,
    "show_ui": true,
    "show_in_menu": true,
    "admin_menu_parent": "",
    "show_in_admin_bar": true,
    "show_in_nav_menus": true,
    "show_in_rest": true,
    "rest_base": "",
    "rest_namespace": "wp\/v2",
    "rest_controller_class": "WP_REST_Posts_Controller",
    "menu_position": "",
    "menu_icon": {
        "type": "dashicons",
        "value": "dashicons-groups"
    },
    "rename_capabilities": false,
    "singular_capability_name": "post",
    "plural_capability_name": "posts",
    "supports": [
        "title",
        "editor",
        "thumbnail",
        "custom-fields"
    ],
    "taxonomies": "",
    "has_archive": false,
    "has_archive_slug": "",
    "rewrite": {
        "permalink_rewrite": "post_type_key",
        "with_front": "1",
        "feeds": "0",
        "pages": "1"
    },
    "query_var": "post_type_key",
    "query_var_name": "",
    "can_export": true,
    "delete_with_user": false,
    "register_meta_box_cb": "",
    "enter_title_here": "",
    "private": true,
    "modified": 1758075249
}
